legit/__init__.py
legit/bootstrap.py
legit/cli.py
legit/core.py
legit/scm.py
legit/settings.py
legit/utils.py
legit-1.2.0.post0.dist-info/AUTHORS
legit-1.2.0.post0.dist-info/LICENSE
legit-1.2.0.post0.dist-info/METADATA
legit-1.2.0.post0.dist-info/WHEEL
legit-1.2.0.post0.dist-info/entry_points.txt
legit-1.2.0.post0.dist-info/top_level.txt
legit-1.2.0.post0.dist-info/RECORD
