Metadata-Version: 2.1
Name: legit
Version: 1.2.0.post0
Summary: Git for Humans.
Home-page: https://github.com/frostming/legit
Author: Kenneth Reitz
Author-email: me@kennethreitz.com
License: BSD
Platform: UNKNOWN
Classifier: Development Status :: 5 - Production/Stable
Classifier: Intended Audience :: Developers
Classifier: Natural Language :: English
Classifier: License :: OSI Approved :: BSD License
Classifier: Programming Language :: Python
Classifier: Programming Language :: Python :: 2
Classifier: Programming Language :: Python :: 2.7
Classifier: Programming Language :: Python :: 3
Classifier: Programming Language :: Python :: 3.5
Classifier: Programming Language :: Python :: 3.6
Classifier: Programming Language :: Python :: 3.7
Classifier: Programming Language :: Python :: 3.8
Requires-Python: >=2.7,!=3.0.*,!=3.1.*,!=3.2.*,!=3.3.*,!=3.4.*
Requires-Dist: click
Requires-Dist: clint
Requires-Dist: crayons
Requires-Dist: GitPython
Requires-Dist: six
